shipyard_thoughtspot/__init__.py
shipyard_thoughtspot/cli/authtest.py
shipyard_thoughtspot/cli/export_answer.py
shipyard_thoughtspot/cli/export_live_report.py
shipyard_thoughtspot/cli/export_metadata.py
shipyard_thoughtspot/cli/search_data.py
shipyard_thoughtspot/thoughtspot.py
shipyard_thoughtspot-0.1.2.dist-info/METADATA
shipyard_thoughtspot-0.1.2.dist-info/WHEEL
shipyard_thoughtspot-0.1.2.dist-info/RECORD
