Metadata-Version: 2.1
Name: shipyard-thoughtspot
Version: 0.1.2
Summary: 
Author: wrp801
Author-email: wespoulsen@gmail.com
Requires-Python: >=3.9,<4.0
Classifier: Programming Language :: Python :: 3
Classifier: Programming Language :: Python :: 3.9
Classifier: Programming Language :: Python :: 3.10
Classifier: Programming Language :: Python :: 3.11
Requires-Dist: pandas (==1.5.3)
Requires-Dist: requests (==2.28.0)
Requires-Dist: shipyard-templates (>=0.1.3,<0.2.0)
